---
layout: page-with-sidebar
title:  "字节码只是表层"
date:   2024-05-21 9:47:03 +0800
author: reflectt6
categories: "编程基础"
mainTag: "编程基础"
secondaryTag: "Java"
hideTag: false
---

## 了解字节码

想更加了解java运行机制就需要了解java字节码了

[知乎](https://zhuanlan.zhihu.com/p/142170303)

```
下面研究了两个简单的例子，感觉java并不会对代码逻辑做过多优化。
- 例如有些没用到的变量，编译时不会删除
- 有些重复用到的函数调用，不会使用常量池存储优化
相比c++的编译优化感觉简陋很多
```

自然产生疑问，一个这么成熟的编程语言，为何这么简单的优化都不做呢？

`Java编译器其实分两类，包括前端编译器（javac）、后端编译器【即时编译器（C1、C2、Graal），提前编译器】`

`前端编译器负责把编程语言转化成字节码，后端编译器负责把字节码转成机器码`

本章看到的字节码是通过javac编译出来的，也就是前端编译器。前端编译器并不会对代码做任何形式的优化，这些优化统统放到了即时编译器（JIT Just In Time）中实现。为什么呢？应该不光是java，还有JRuby、Groovy、Scala等语言也会生成字节码。在JIT中对代码进行优化，则这些语言都可以吃到红利。

`前端编译也不是一点优化都不做，例如if(false)这种必然走不到的分支会被删除，其实这点算是java版本的条件编译了。`



### 分层编译

从左到右编译所需资源依次提升，机器码性能依次提升

解释器->C1编译器(client compiler)->C2编译器(server compiler)



### [查看java机器码](https://blog.csdn.net/baidu_28523317/article/details/103849732)

#### 1、命令行方式

```shell
java -XX:+UnlockDiagnosticVMOptions -XX:+PrintCompilation -XX:+LogCompilation -XX:+PrintAssembly org.example.Main
```

显示汇编需要hsdis包，可以在[这里下载](https://chriswhocodes.com/hsdis/)。

#### 2、[JITWatch插件](https://github.com/AdoptOpenJDK/jitwatch/wiki)

[这里下载](https://github.com/AdoptOpenJDK/jitwatch/releases)

通过下面的命令运行

```shell
java -jar jitwatch-ui-1.4.9-shaded-<OS>-<ARCH>.jar
```

注意：需要使用JDK11+的版本运行，否则需要额外安装JavaFX。

[使用参考](https://www.cnblogs.com/flydean/p/jvm-jit-jitwatch.html)

我简单使用了一下，太简单的代码不会显示TriView，换句话说太简单的代码不会触发即时编译。那么自然想到什么样的代码是简单的？`即时编译的目标是 -- 热点代码`，包括：

- 多次调用的方法
- 多次执行的循环体

图方便可以直接用sandbox文件夹中的demo测试.



### IDEA工具

- 可以通过`View` ->`show bytecode`调用idea自带的字节码解释工具（需要提前编译完成）
- 通过下载插件`jclasslib`可以查看常量池、符号表等信息

### Demo入门

来看个最简单的例子

```java
package org.example;

public class Main {
    public static void main(String[] args) {
        System.out.println("Hello world!");
    }
}
```

通过工具得到字节码

```java
// class version 52.0 (52)
// access flags 0x21
public class org/example/Main {

  // compiled from: Main.java

  // access flags 0x1
  public <init>()V
   L0
    LINENUMBER 3 L0
    ALOAD 0
    INVOKESPECIAL java/lang/Object.<init> ()V
    RETURN
   L1
    LOCALVARIABLE this Lorg/example/Main; L0 L1 0
    MAXSTACK = 1
    MAXLOCALS = 1

  // access flags 0x9
  public static main([Ljava/lang/String;)V
   L0
    LINENUMBER 5 L0
    GETSTATIC java/lang/System.out : Ljava/io/PrintStream;
    LDC "Hello world!"
    INVOKEVIRTUAL java/io/PrintStream.println (Ljava/lang/String;)V
   L1
    LINENUMBER 6 L1
    RETURN
   L2
    LOCALVARIABLE args [Ljava/lang/String; L0 L2 0
    MAXSTACK = 2
    MAXLOCALS = 1
}
```

#### 1、L0等标记

L0、L1、L2等标签是字节码中的标记，用来表示代码执行的不同位置。这些标签有助于控制流的管理和调试信息的生成。具体来说：

- **L0, L1, L2**等标签定义了字节码指令中的位置，类似于代码中的行号或标签。
- 这些标签被用来指示跳转指令（如`goto`）、条件跳转（如`if`指令）和局部变量范围等。

在你提供的代码中，L0、L1、L2的作用如下：

```java
public <init>()V
 L0
  LINENUMBER 3 L0
  ALOAD 0
  INVOKESPECIAL java/lang/Object.<init> ()V
  RETURN
 L1
  LOCALVARIABLE this Lorg/example/Main; L0 L1 0
  MAXSTACK = 1
  MAXLOCALS = 1
```

- `L0` 是一个标签，标记了构造函数的开始位置。
- `LINENUMBER 3 L0` 表示这个标签对应于源代码的第3行。
- `ALOAD 0` 到 `RETURN` 之间的字节码指令在这个标签的范围内执行。
- `L1` 是另一个标签，标记了构造函数的结束位置。
- `LOCALVARIABLE this Lorg/example/Main; L0 L1 0` 声明了 `this` 局部变量的生存期是从 `L0` 到 `L1`。

```java
public static main([Ljava/lang/String;)V
 L0
  LINENUMBER 5 L0
  GETSTATIC java/lang/System.out : Ljava/io/PrintStream;
  LDC "Hello world!"
  INVOKEVIRTUAL java/io/PrintStream.println (Ljava/lang/String;)V
 L1
  LINENUMBER 6 L1
  RETURN
 L2
  LOCALVARIABLE args [Ljava/lang/String; L0 L2 0
  MAXSTACK = 2
  MAXLOCALS = 1
```

- `L0` 是一个标签，标记了`main`方法的开始位置。
- `LINENUMBER 5 L0` 表示这个标签对应于源代码的第5行。
- 从 `GETSTATIC` 到 `INVOKEVIRTUAL` 的指令在这个标签的范围内执行。
- `L1` 是另一个标签，标记了 `main` 方法的 `RETURN` 位置，对应源代码的第6行。
- `L2` 是一个标签，标记了`main`方法的结束位置。
- `LOCALVARIABLE args [Ljava/lang/String; L0 L2 0` 声明了 `args` 局部变量的生存期是从 `L0` 到 `L2`。

#### 2、整体解释

这个文件是一个Java类文件的反编译结果，表示为一种中间语言（通常称为Java字节码）。以下是对其各部分的解释：

```java
// class version 52.0 (52)
// access flags 0x21
public class org/example/Main {
```

- `class version 52.0 (52)` 表示这个类文件是用Java 8编译的。每个Java版本都有一个对应的类文件版本号，52代表Java 8。
- `access flags 0x21` 表示这个类的访问标志。0x21表示这是一个`public`类并且它是`super`类。

```java
  // compiled from: Main.java
```

- 表示这个类是从名为`Main.java`的源文件编译而来的。

```java
  // access flags 0x1
  public <init>()V
```

- 这是类的构造函数。`access flags 0x1` 表示这个构造函数是`public`的。
- `<init>()V` 是构造函数的方法签名，其中`<init>`是构造函数的名称，`()`表示它没有参数，`V`表示它没有返回值（`void`）。

```java
   L0
    LINENUMBER 3 L0
    ALOAD 0
    INVOKESPECIAL java/lang/Object.<init> ()V
    RETURN
   L1
    LOCALVARIABLE this Lorg/example/Main; L0 L1 0
    MAXSTACK = 1
    MAXLOCALS = 1
```

- 这些是构造函数的字节码指令。
- `LINENUMBER 3 L0`：指示源代码中的行号，用于调试。
- `ALOAD 0`：将局部变量表中索引为0的引用加载到操作数栈上。对于实例方法，索引0处是`this`引用。
- `INVOKESPECIAL java/lang/Object.<init> ()V`：调用超类（`Object`类）的构造函数。
- `RETURN`：从构造函数返回。
- `LOCALVARIABLE this Lorg/example/Main; L0 L1 0`：局部变量表中声明了一个`this`变量，它是`org/example/Main`类型的，从L0到L1的范围。
- `MAXSTACK = 1` 和 `MAXLOCALS = 1`：表示这个方法在执行时最多需要1个操作数栈元素和1个局部变量。

```java
  // access flags 0x9
  public static main([Ljava/lang/String;)V
```

- 这是主方法（`main`方法）的声明。`access flags 0x9` 表示这个方法是`public static`的。
- `main([Ljava/lang/String;)V`：方法签名，`main`是方法名，`([Ljava/lang/String;)`表示它接收一个`String`数组作为参数，`V`表示返回值为`void`。

```java
   L0
    LINENUMBER 5 L0
    GETSTATIC java/lang/System.out : Ljava/io/PrintStream;
    LDC "Hello world!"
    INVOKEVIRTUAL java/io/PrintStream.println (Ljava/lang/String;)V
   L1
    LINENUMBER 6 L1
    RETURN
   L2
    LOCALVARIABLE args [Ljava/lang/String; L0 L2 0
    MAXSTACK = 2
    MAXLOCALS = 1
}
```

- 这些是主方法的字节码指令。
- `LINENUMBER 5 L0`：指示源代码中的行号5。
- `GETSTATIC java/lang/System.out : Ljava/io/PrintStream;`：获取`System.out`静态字段的引用，它是`PrintStream`类型。
- `LDC "Hello world!"`：将字符串字面量"Hello world!"加载到操作数栈上。
- `INVOKEVIRTUAL java/io/PrintStream.println (Ljava/lang/String;)V`：调用`PrintStream`类的`println`方法来打印字符串。
- `RETURN`：从方法返回。
- `LOCALVARIABLE args [Ljava/lang/String; L0 L2 0`：局部变量表中声明了一个`args`变量，它是一个`String`数组，从L0到L2的范围。
- `MAXSTACK = 2` 和 `MAXLOCALS = 1`：表示这个方法在执行时最多需要2个操作数栈元素和1个局部变量。



### Demo2 

#### 源代码

```java
package org.example;

import java.util.ArrayList;
import java.util.Arrays;
import java.util.List;

public class Main {

    static List<Integer> li = new ArrayList<>();

    public static void main(String[] args) {
        li.add(1);
        li.add(2);
        li.add(3);
        li.add(4);
        li.add(5);
	      li.add(6);

        int[] b = new int[li.size()];
        int[] c = new int[li.size()];
        int[] d = new int[li.size()];

        for (int i = 0; i < li.size(); i++) {
            System.out.println("b[i] = " + b[i]);
            System.out.println("c[i] = " + c[i]);
            System.out.println("d[i] = " + d[i]);
        }
    }
}
```

#### 字节码

```java
// class version 52.0 (52)
// access flags 0x21
public class org/example/Main {

  // compiled from: Main.java

  // access flags 0x8
  // signature Ljava/util/List<Ljava/lang/Integer;>;
  // declaration: li extends java.util.List<java.lang.Integer>
  static Ljava/util/List; li

  // access flags 0x1
  public <init>()V
   L0
    LINENUMBER 7 L0
    ALOAD 0
    INVOKESPECIAL java/lang/Object.<init> ()V
    RETURN
   L1
    LOCALVARIABLE this Lorg/example/Main; L0 L1 0
    MAXSTACK = 1
    MAXLOCALS = 1

  // access flags 0x9
  public static main([Ljava/lang/String;)V
   L0
    LINENUMBER 12 L0
    GETSTATIC org/example/Main.li : Ljava/util/List;
    ICONST_1
    INVOKESTATIC java/lang/Integer.valueOf (I)Ljava/lang/Integer;
    INVOKEINTERFACE java/util/List.add (Ljava/lang/Object;)Z (itf)
    POP
   L1
    LINENUMBER 13 L1
    GETSTATIC org/example/Main.li : Ljava/util/List;
    ICONST_2
    INVOKESTATIC java/lang/Integer.valueOf (I)Ljava/lang/Integer;
    INVOKEINTERFACE java/util/List.add (Ljava/lang/Object;)Z (itf)
    POP
   L2
    LINENUMBER 14 L2
    GETSTATIC org/example/Main.li : Ljava/util/List;
    ICONST_3
    INVOKESTATIC java/lang/Integer.valueOf (I)Ljava/lang/Integer;
    INVOKEINTERFACE java/util/List.add (Ljava/lang/Object;)Z (itf)
    POP
   L3
    LINENUMBER 15 L3
    GETSTATIC org/example/Main.li : Ljava/util/List;
    ICONST_4
    INVOKESTATIC java/lang/Integer.valueOf (I)Ljava/lang/Integer;
    INVOKEINTERFACE java/util/List.add (Ljava/lang/Object;)Z (itf)
    POP
   L4
    LINENUMBER 16 L4
    GETSTATIC org/example/Main.li : Ljava/util/List;
    ICONST_5
    INVOKESTATIC java/lang/Integer.valueOf (I)Ljava/lang/Integer;
    INVOKEINTERFACE java/util/List.add (Ljava/lang/Object;)Z (itf)
    POP
   L5
    LINENUMBER 17 L5
    GETSTATIC org/example/Main.li : Ljava/util/List;
    BIPUSH 6
    INVOKESTATIC java/lang/Integer.valueOf (I)Ljava/lang/Integer;
    INVOKEINTERFACE java/util/List.add (Ljava/lang/Object;)Z (itf)
    POP
   L6
    LINENUMBER 19 L6
    GETSTATIC org/example/Main.li : Ljava/util/List;
    INVOKEINTERFACE java/util/List.size ()I (itf)
    NEWARRAY T_INT
    ASTORE 1
   L7
    LINENUMBER 20 L7
    GETSTATIC org/example/Main.li : Ljava/util/List;
    INVOKEINTERFACE java/util/List.size ()I (itf)
    NEWARRAY T_INT
    ASTORE 2
   L8
    LINENUMBER 21 L8
    GETSTATIC org/example/Main.li : Ljava/util/List;
    INVOKEINTERFACE java/util/List.size ()I (itf)
    NEWARRAY T_INT
    ASTORE 3
   L9
    LINENUMBER 23 L9
    ICONST_0
    ISTORE 4
   L10
   FRAME FULL [[Ljava/lang/String; [I [I [I I] []
    ILOAD 4
    GETSTATIC org/example/Main.li : Ljava/util/List;
    INVOKEINTERFACE java/util/List.size ()I (itf)
    IF_ICMPGE L11
   L12
    LINENUMBER 24 L12
    GETSTATIC java/lang/System.out : Ljava/io/PrintStream;
    NEW java/lang/StringBuilder
    DUP
    INVOKESPECIAL java/lang/StringBuilder.<init> ()V
    LDC "b[i] = "
    INVOKEVIRTUAL java/lang/StringBuilder.append (Ljava/lang/String;)Ljava/lang/StringBuilder;
    ALOAD 1
    ILOAD 4
    IALOAD
    INVOKEVIRTUAL java/lang/StringBuilder.append (I)Ljava/lang/StringBuilder;
    INVOKEVIRTUAL java/lang/StringBuilder.toString ()Ljava/lang/String;
    INVOKEVIRTUAL java/io/PrintStream.println (Ljava/lang/String;)V
   L13
    LINENUMBER 25 L13
    GETSTATIC java/lang/System.out : Ljava/io/PrintStream;
    NEW java/lang/StringBuilder
    DUP
    INVOKESPECIAL java/lang/StringBuilder.<init> ()V
    LDC "c[i] = "
    INVOKEVIRTUAL java/lang/StringBuilder.append (Ljava/lang/String;)Ljava/lang/StringBuilder;
    ALOAD 2
    ILOAD 4
    IALOAD
    INVOKEVIRTUAL java/lang/StringBuilder.append (I)Ljava/lang/StringBuilder;
    INVOKEVIRTUAL java/lang/StringBuilder.toString ()Ljava/lang/String;
    INVOKEVIRTUAL java/io/PrintStream.println (Ljava/lang/String;)V
   L14
    LINENUMBER 26 L14
    GETSTATIC java/lang/System.out : Ljava/io/PrintStream;
    NEW java/lang/StringBuilder
    DUP
    INVOKESPECIAL java/lang/StringBuilder.<init> ()V
    LDC "d[i] = "
    INVOKEVIRTUAL java/lang/StringBuilder.append (Ljava/lang/String;)Ljava/lang/StringBuilder;
    ALOAD 3
    ILOAD 4
    IALOAD
    INVOKEVIRTUAL java/lang/StringBuilder.append (I)Ljava/lang/StringBuilder;
    INVOKEVIRTUAL java/lang/StringBuilder.toString ()Ljava/lang/String;
    INVOKEVIRTUAL java/io/PrintStream.println (Ljava/lang/String;)V
   L15
    LINENUMBER 23 L15
    IINC 4 1
    GOTO L10
   L11
    LINENUMBER 28 L11
   FRAME CHOP 1
    RETURN
   L16
    LOCALVARIABLE i I L10 L11 4
    LOCALVARIABLE args [Ljava/lang/String; L0 L16 0
    LOCALVARIABLE b [I L7 L16 1
    LOCALVARIABLE c [I L8 L16 2
    LOCALVARIABLE d [I L9 L16 3
    MAXSTACK = 4
    MAXLOCALS = 5

  // access flags 0x8
  static <clinit>()V
   L0
    LINENUMBER 9 L0
    NEW java/util/ArrayList
    DUP
    INVOKESPECIAL java/util/ArrayList.<init> ()V
    PUTSTATIC org/example/Main.li : Ljava/util/List;
    RETURN
    MAXSTACK = 2
    MAXLOCALS = 0
}
```

#### 解释：

###### 静态字段声明

```java
// access flags 0x8
// signature Ljava/util/List<Ljava/lang/Integer;>;
// declaration: li extends java.util.List<java.lang.Integer>
static Ljava/util/List; li
```

- `access flags 0x8`表示这是一个`static`字段。
- `signature Ljava/util/List<Ljava/lang/Integer;>;`表示`li`是一个`List`，存储的是`Integer`对象。
- `li`是类的一个静态字段。



##### li.add(6);

```
L5
 LINENUMBER 17 L5
 GETSTATIC org/example/Main.li : Ljava/util/List;
 BIPUSH 6
 INVOKESTATIC java/lang/Integer.valueOf (I)Ljava/lang/Integer;
 INVOKEINTERFACE java/util/List.add (Ljava/lang/Object;)Z (itf)
 POP
```

- `L5`
  - 这是一个标签，标记了这段字节码的开始位置。
- `LINENUMBER 17 L5`
  - 这个指令表示标签`L5`对应于源代码中的第17行。这是调试信息，用于在调试器中显示行号。
- `GETSTATIC org/example/Main.li : Ljava/util/List;`
  - 这条指令从类`org/example/Main`中获取静态字段`li`，它是一个`List`类型的对象。将这个列表引用压入操作数栈。
- `BIPUSH 6`
  - 这条指令将整数常量6压入操作数栈。`BIPUSH` 用于处理-128到127之间的常量值。
- `INVOKESTATIC java/lang/Integer.valueOf (I)Ljava/lang/Integer;`
  - 这条指令调用`Integer`类的静态方法`valueOf`，将栈顶的整数6转换为`Integer`对象。这个方法的签名表示它接受一个整数参数（`I`）并返回一个`Integer`对象（`Ljava/lang/Integer;`）。
- `INVOKEINTERFACE java/util/List.add (Ljava/lang/Object;)Z (itf)`
  - 这条指令调用`List`接口的`add`方法，将`Integer`对象添加到列表中。方法签名`(Ljava/lang/Object;)Z`表示它接受一个`Object`参数并返回一个布尔值（`Z`表示`boolean`）。
  - `(itf)`表示这是一个接口方法调用。
- `POP`
  - 这条指令弹出栈顶的值（在这里是`List.add`方法的返回值），因为我们并不需要用到这个返回值。



##### li.add(5);

```
   L4
    LINENUMBER 16 L4
    GETSTATIC org/example/Main.li : Ljava/util/List;
    ICONST_5
    INVOKESTATIC java/lang/Integer.valueOf (I)Ljava/lang/Integer;
    INVOKEINTERFACE java/util/List.add (Ljava/lang/Object;)Z (itf)
    POP
```

`ICONST_5`：这条指令将整数常量5压入操作数栈。`ICONST_5` 是一种快捷指令，用于处理常量值0到5。

##### 静态代码块初始化

```java
// access flags 0x8
  static <clinit>()V
   L0
    LINENUMBER 9 L0
    NEW java/util/ArrayList
    DUP
    INVOKESPECIAL java/util/ArrayList.<init> ()V
    PUTSTATIC org/example/Main.li : Ljava/util/List;
    RETURN
    MAXSTACK = 2
    MAXLOCALS = 0
```

`L0`：这是一个标签，标记了这段字节码的开始位置。

`LINENUMBER 9 L0`：这个指令表示标签`L0`对应于源代码中的第9行。这是调试信息，用于在调试器中显示行号。

`NEW java/util/ArrayList`：这条指令创建一个新的`ArrayList`对象，并将其引用压入操作数栈顶。

`DUP`：这条指令复制操作数栈顶的值（即刚刚创建的`ArrayList`对象的引用），并将副本压入操作数栈顶。这样做是为了在创建对象后保留一个引用以便后续使用。

`INVOKESPECIAL java/util/ArrayList.<init> ()V`：这条指令调用`ArrayList`类的构造函数，对新创建的`ArrayList`对象进行初始化。

`PUTSTATIC org/example/Main.li : Ljava/util/List;`：这条指令将操作数栈顶的值（即初始化后的`ArrayList`对象的引用）存储到静态字段`li`中。

`RETURN`：这条指令表示方法执行结束，返回到调用者。

`MAXSTACK = 2`：这个指令表示方法运行时操作数栈的最大深度为2。

`MAXLOCALS = 0`：这个指令表示方法中局部变量表的最大大小为0，因为这个方法没有使用局部变量。



##### 循环

```java
L9
 LINENUMBER 23 L9
 ICONST_0
 ISTORE 4
```

- `L9`：这是一个标签，标记了这段字节码的开始位置。
- `LINENUMBER 23 L9`：这个指令表示标签`L9`对应于源代码中的第23行。这是调试信息，用于在调试器中显示行号。
- `ICONST_0`：这条指令将整数常量0压入操作数栈。它是一种快捷指令，用于处理整数常量0到5。
- `ISTORE 4`：这条指令将操作数栈顶的值（即刚刚加载的整数0）存储到局部变量表的索引4处。在这里，它用于初始化一个循环计数器。

```java
L10
 FRAME FULL [[Ljava/lang/String; [I [I [I I] []
 ILOAD 4
 GETSTATIC org/example/Main.li : Ljava/util/List;
 INVOKEINTERFACE java/util/List.size ()I (itf)
 IF_ICMPGE L11
```

- `FRAME FULL [[Ljava/lang/String; [I [I [I I] []`：这个指令表示当前帧的局部变量表和操作数栈的状态。这个信息用于调试和异常处理。
- `ILOAD 4`：这条指令将局部变量表索引为4的值（即循环计数器）加载到操作数栈顶。
- `GETSTATIC org/example/Main.li : Ljava/util/List;`：这条指令获取静态字段`li`，它是一个`java/util/List`类型的对象，将其引用压入操作数栈顶。
- `INVOKEINTERFACE java/util/List.size ()I (itf)`：这条指令调用`List`接口的`size`方法，获取列表的大小，并将结果压入操作数栈顶。
- `IF_ICMPGE L11`：这条指令将比较操作数栈顶的两个整数值，如果第一个值大于或等于第二个值，则跳转到标签`L11`；否则继续执行下一条指令。

```java
L12
 LINENUMBER 24 L12
 GETSTATIC java/lang/System.out : Ljava/io/PrintStream;
 NEW java/lang/StringBuilder
 DUP
 INVOKESPECIAL java/lang/StringBuilder.<init> ()V
 LDC "b[i] = "
 INVOKEVIRTUAL java/lang/StringBuilder.append (Ljava/lang/String;)Ljava/lang/StringBuilder;
 ALOAD 1
 ILOAD 4
 IALOAD
 INVOKEVIRTUAL java/lang/StringBuilder.append (I)Ljava/lang/StringBuilder;
 INVOKEVIRTUAL java/lang/StringBuilder.toString ()Ljava/lang/String;
 INVOKEVIRTUAL java/io/PrintStream.println (Ljava/lang/String;)V
```

- `LINENUMBER 24 L12`：这个指令表示标签`L12`对应于源代码中的第24行。这是调试信息，用于在调试器中显示行号。
- `GETSTATIC java/lang/System.out : Ljava/io/PrintStream;`：这条指令获取`System.out`，即标准输出流。
- `NEW java/lang/StringBuilder`：这条指令创建一个新的`StringBuilder`对象，并将其引用压入操作数栈顶。
- `DUP`：这条指令复制操作数栈顶的值（即刚刚创建的`StringBuilder`对象的引用），并将副本压入操作数栈顶。
- `INVOKESPECIAL java/lang/StringBuilder.<init> ()V`：这条指令调用`StringBuilder`类的构造函数，对新创建的`StringBuilder`对象进行初始化。
- `LDC "b[i] = "`：这条指令将字符串常量"b[i] = "压入操作数栈顶。
- `INVOKEVIRTUAL java/lang/StringBuilder.append (Ljava/lang/String;)Ljava/lang/StringBuilder;`：这条指令调用`StringBuilder`对象的`append`方法，将字符串常量追加到`StringBuilder`对象中。
- `ALOAD 1`：这条指令将局部变量表索引为1的值（即数组`b`的引用）加载到操作数栈顶。
- `ILOAD 4`：这条指令将局部变量表索引为4的值（即循环计数器）加载到操作数栈顶。
- `IALOAD`：这条指令将整数数组中索引为循环计数器的元素加载到操作数栈顶。
- `INVOKEVIRTUAL java/lang/StringBuilder.append (I)Ljava/lang/StringBuilder;`：这条指令调用`StringBuilder`对象的`append`方法，将整数数组元素的值追加到`StringBuilder`对象中。INVOKEVIRTUAL java/lang/StringBuilder.append (I)Ljava/lang/StringBuilder;：这条指令调用StringBuilder对象的append方法，将整数数组元素的值追加到StringBuilder对象中。
- `INVOKEVIRTUAL java/lang/StringBuilder.toString ()Ljava/lang/String;`：这条指令调用`StringBuilder`对象的`toString`方法，将`StringBuilder`对象转换为`String`对象。
- `INVOKEVIRTUAL java/io/PrintStream.println (Ljava/lang/String;)V`：这条指令调用`PrintStream`对象的`println`方法，将字符串对象打印到控制台。

```
L15
 LINENUMBER 23 L15
 IINC 4 1
 GOTO L10
```

- `L15`：这是一个标签，标记了这段字节码的开始位置。
- `LINENUMBER 23 L15`：这个指令表示标签`L15`对应于源代码中的第23行。这是调试信息，用于在调试器中显示行号。
- `IINC 4 1`：这条指令将局部变量表索引为4的值（即循环计数器）增加1。
- `GOTO L10`：这条指令无条件跳转到标签`L10`，即回到循环的开头。

```java
L11
 LINENUMBER 28 L11
 FRAME CHOP 1
 RETURN
```

- `L11`：这是一个标签，标记了方法结束的位置。
- `LINENUMBER 28 L11`：这个指令表示标签`L11`对应于源代码中的第28行。这是调试信息，用于在调试器中显示行号。
- `FRAME CHOP 1`：这个指令表示当前帧的局部变量表和操作数栈的状态。在这里，它告诉虚拟机丢弃了一个局部变量（循环计数器）。
- `RETURN`：这条指令表示方法执行结束，返回到调用者。

```java
L16
 LOCALVARIABLE i I L10 L11 4
 LOCALVARIABLE args [Ljava/lang/String; L0 L16 0
 LOCALVARIABLE b [I L7 L16 1
 LOCALVARIABLE c [I L8 L16 2
 LOCALVARIABLE d [I L9 L16 3
 MAXSTACK = 4
 MAXLOCALS = 5
```

- `LOCALVARIABLE i I L10 L11 4`：这个指令声明了一个局部变量`i`，它的作用域从标签`L10`到标签`L11`，索引为4。
- `LOCALVARIABLE args [Ljava/lang/String; L0 L16 0`：这个指令声明了一个局部变量`args`，它的作用域从标签`L0`到标签`L16`，索引为0。
- `LOCALVARIABLE b [I L7 L16 1`：这个指令声明了一个局部变量`b`，它的作用域从标签`L7`到标签`L16`，索引为1。
- `LOCALVARIABLE c [I L8 L16 2`：这个指令声明了一个局部变量`c`，它的作用域从标签`L8`到标签`L16`，索引为2。
- `LOCALVARIABLE d [I L9 L16 3`：这个指令声明了一个局部变量`d`，它的作用域从标签`L9`到标签`L16`，索引为3。
- `MAXSTACK = 4`：这个指令表示方法运行时操作数栈的最大深度为4。
- `MAXLOCALS = 5`：这个指令表示方法中局部变量表的最大大小为5。



